kobject/__init__.py
kobject/validator.py
kobject-0.6.6.dist-info/METADATA
kobject-0.6.6.dist-info/WHEEL
kobject-0.6.6.dist-info/licenses/LICENSE
kobject-0.6.6.dist-info/RECORD
