Metadata-Version: 2.4
Name: kobject
Version: 0.6.6
Summary: Know your object is a attribute type checker
License: Apache-2.0
License-File: LICENSE
Author: Marco Sievers de Almeida Ximit Gaia
Author-email: im.ximit@gmail.com
Requires-Python: >=3.10,<4.0
Classifier: License :: OSI Approved :: Apache Software License
Classifier: Programming Language :: Python :: 3
Classifier: Programming Language :: Python :: 3.10
Classifier: Programming Language :: Python :: 3.11
Classifier: Programming Language :: Python :: 3.12
Classifier: Programming Language :: Python :: 3.13
Classifier: Programming Language :: Python :: 3.14
Project-URL: bugs, https://github.com/CenturyBoys/kobject/issues
Project-URL: documentation, https://github.com/CenturyBoys/kobject/blob/main/README.md
Project-URL: homepage, https://github.com/CenturyBoys/kobject
Project-URL: repository, https://github.com/CenturyBoys/kobject/tree/main
